pynimation/__init__.py
pynimation/__main__.py
pynimation-0.0.1.dist-info/METADATA
pynimation-0.0.1.dist-info/WHEEL
pynimation-0.0.1.dist-info/entry_points.txt
pynimation-0.0.1.dist-info/top_level.txt
pynimation-0.0.1.dist-info/RECORD
